arisia/__init__.py
arisia/load.py
arisia-1.0.5.dist-info/METADATA
arisia-1.0.5.dist-info/WHEEL
arisia-1.0.5.dist-info/top_level.txt
arisia-1.0.5.dist-info/RECORD
